django_environs/__init__.py
django_environs/__main__.py
django_environs/template.py
django_environs/management/__init__.py
django_environs/management/commands/startproject.py
django_environs-0.1.1.dist-info/entry_points.txt
django_environs-0.1.1.dist-info/LICENSE
django_environs-0.1.1.dist-info/WHEEL
django_environs-0.1.1.dist-info/METADATA
django_environs-0.1.1.dist-info/RECORD
